pibooth_sound_effects/__init__.py
pibooth_sound_effects/pibooth_sound_effects.py
pibooth_sound_effects/sounds/capture.wav
pibooth_sound_effects/sounds/choose.wav
pibooth_sound_effects/sounds/chosen.wav
pibooth_sound_effects/sounds/finish.wav
pibooth_sound_effects/sounds/preview_countdown.wav
pibooth_sound_effects-0.0.4.dist-info/LICENSE
pibooth_sound_effects-0.0.4.dist-info/METADATA
pibooth_sound_effects-0.0.4.dist-info/WHEEL
pibooth_sound_effects-0.0.4.dist-info/entry_points.txt
pibooth_sound_effects-0.0.4.dist-info/top_level.txt
pibooth_sound_effects-0.0.4.dist-info/zip-safe
pibooth_sound_effects-0.0.4.dist-info/RECORD
