Metadata-Version: 2.1
Name: pibooth-sound-effects
Version: 0.0.4
Summary: Pibooth plugin to add sound effects.
Home-page: https://github.com/pibooth/pibooth-sound-effects
Author: Vincent Verdeil, Antoine Rousseaux
License: GPLv3
Download-URL: https://github.com/pibooth/pibooth-sound-effects/archive/0.0.4.tar.gz
Keywords: Raspberry Pi,camera,photobooth,pygame
Platform: unix
Platform: linux
Classifier: Development Status :: 5 - Production/Stable
Classifier: Environment :: Plugins
Classifier: Intended Audience :: Developers
Classifier: Intended Audience :: End Users/Desktop
Classifier: License :: OSI Approved :: GNU Affero General Public License v3
Classifier: Natural Language :: English
Classifier: Operating System :: POSIX :: Linux
Classifier: Programming Language :: Python :: 3.6
Classifier: Programming Language :: Python :: 3.7
Classifier: Programming Language :: Python :: 3.8
Classifier: Programming Language :: Python :: 3.9
Classifier: Topic :: Multimedia :: Graphics :: Capture :: Digital Camera
Requires-Python: >=3.6
Requires-Dist: pibooth (>=2.0.0)
